<?xml version = '1.0' encoding = 'UTF-8'?>
<TableProxySqlServerv2k5 class="oracle.dbtools.crest.model.design.storage.sqlserver.v2k5.TableProxySqlServerv2k5" name="L_MAT_PROVEEDOR" directorySegmentName="seg_0" id="BFCEEC1F-A3BB-F9E0-14AE-F75215088374">
<createdBy>Lenovo</createdBy>
<createdTime>2018-04-09 20:49:53 UTC</createdTime>
<ownerDesignName>Diagrama de clases</ownerDesignName>
<database>DB_NULLELEMENT</database>
<schema>97B4F732-273A-99B3-D710-C0B970573B84</schema>
<columnProxies>
<ColumnProxy class="oracle.dbtools.crest.model.design.storage.sqlserver.v2k12.ColumnProxySqlServerv2k12" name="CANTIDAD" id="055FCD31-4387-AF25-5FF8-FC513BD50BFA">
<createdBy>Lenovo</createdBy>
<createdTime>2018-04-09 20:49:53 UTC</createdTime>
<ownerDesignName>Diagrama de clases</ownerDesignName>
</ColumnProxy>
<ColumnProxy class="oracle.dbtools.crest.model.design.storage.sqlserver.v2k12.ColumnProxySqlServerv2k12" name="UNIDAD_MEDIDA" id="08A002E6-BC53-E0A5-1450-4B328096C540">
<createdBy>Lenovo</createdBy>
<createdTime>2018-04-09 20:49:53 UTC</createdTime>
<ownerDesignName>Diagrama de clases</ownerDesignName>
</ColumnProxy>
<ColumnProxy class="oracle.dbtools.crest.model.design.storage.sqlserver.v2k12.ColumnProxySqlServerv2k12" name="COSTO" id="23D23287-A6A0-7E49-DA25-F8172F04EAC9">
<createdBy>Lenovo</createdBy>
<createdTime>2018-04-09 20:49:53 UTC</createdTime>
<ownerDesignName>Diagrama de clases</ownerDesignName>
</ColumnProxy>
<ColumnProxy class="oracle.dbtools.crest.model.design.storage.sqlserver.v2k12.ColumnProxySqlServerv2k12" name="ID_PROVEEDOR" id="3B916A00-E81A-ED25-DC5D-50952326B7F2">
<createdBy>Lenovo</createdBy>
<createdTime>2018-04-09 20:49:53 UTC</createdTime>
<ownerDesignName>Diagrama de clases</ownerDesignName>
</ColumnProxy>
<ColumnProxy class="oracle.dbtools.crest.model.design.storage.sqlserver.v2k12.ColumnProxySqlServerv2k12" name="ID_LINEA" id="3F9BE41B-CE16-FB68-E89D-996C376FA177">
<createdBy>Lenovo</createdBy>
<createdTime>2018-04-09 20:49:53 UTC</createdTime>
<ownerDesignName>Diagrama de clases</ownerDesignName>
</ColumnProxy>
<ColumnProxy class="oracle.dbtools.crest.model.design.storage.sqlserver.v2k12.ColumnProxySqlServerv2k12" name="CODIGO" id="449EB479-DED0-742A-4307-60E96F5FCB84">
<createdBy>Lenovo</createdBy>
<createdTime>2018-04-09 20:49:53 UTC</createdTime>
<ownerDesignName>Diagrama de clases</ownerDesignName>
</ColumnProxy>
<ColumnProxy class="oracle.dbtools.crest.model.design.storage.sqlserver.v2k12.ColumnProxySqlServerv2k12" name="FECHA_ULT_MOD" id="4AEB640B-CA81-169B-6FB3-843DDE7DA9E3">
<createdBy>Lenovo</createdBy>
<createdTime>2018-04-09 20:49:53 UTC</createdTime>
<ownerDesignName>Diagrama de clases</ownerDesignName>
</ColumnProxy>
<ColumnProxy class="oracle.dbtools.crest.model.design.storage.sqlserver.v2k12.ColumnProxySqlServerv2k12" name="ID_ULT_MOD" id="53136C8B-2C1E-1C11-E0CB-437E1E126651">
<createdBy>Lenovo</createdBy>
<createdTime>2018-04-09 20:49:53 UTC</createdTime>
<ownerDesignName>Diagrama de clases</ownerDesignName>
</ColumnProxy>
<ColumnProxy class="oracle.dbtools.crest.model.design.storage.sqlserver.v2k12.ColumnProxySqlServerv2k12" name="ID_FACTURA" id="5E421C97-45B4-53BC-2B08-87E1AA403AA0">
<createdBy>Lenovo</createdBy>
<createdTime>2018-04-09 20:49:53 UTC</createdTime>
<ownerDesignName>Diagrama de clases</ownerDesignName>
</ColumnProxy>
<ColumnProxy class="oracle.dbtools.crest.model.design.storage.sqlserver.v2k12.ColumnProxySqlServerv2k12" name="FECHA_REGISTRO" id="B2BBA200-B67E-B9A2-80B6-AF67DDFD07EB">
<createdBy>Lenovo</createdBy>
<createdTime>2018-04-09 20:49:53 UTC</createdTime>
<ownerDesignName>Diagrama de clases</ownerDesignName>
</ColumnProxy>
<ColumnProxy class="oracle.dbtools.crest.model.design.storage.sqlserver.v2k12.ColumnProxySqlServerv2k12" name="COSTO_TOTAL" id="C1744D51-A630-B47D-9068-49C2AA966756">
<createdBy>Lenovo</createdBy>
<createdTime>2018-04-09 20:49:53 UTC</createdTime>
<ownerDesignName>Diagrama de clases</ownerDesignName>
</ColumnProxy>
<ColumnProxy class="oracle.dbtools.crest.model.design.storage.sqlserver.v2k12.ColumnProxySqlServerv2k12" name="ID_REGISTRO" id="D4BF3776-60E2-D602-8990-55B016F0D5BC">
<createdBy>Lenovo</createdBy>
<createdTime>2018-04-09 20:49:53 UTC</createdTime>
<ownerDesignName>Diagrama de clases</ownerDesignName>
</ColumnProxy>
</columnProxies>
<foreignKeys>
<ForeignKey class="oracle.dbtools.crest.model.design.storage.sqlserver.v2k5.FKProxySqlServerv2k5" name="FK_L_MAT_PROV_FACT_ID_FACTURA" id="0357736A-D4C0-055A-1BD9-3217B84F53CD">
<createdBy>Lenovo</createdBy>
<createdTime>2018-04-09 20:49:53 UTC</createdTime>
<ownerDesignName>script_JDeveloper</ownerDesignName>
</ForeignKey>
<ForeignKey class="oracle.dbtools.crest.model.design.storage.sqlserver.v2k5.FKProxySqlServerv2k5" name="L_MAT_PROVEEDOR_FK1" id="AAD4B7CD-7CD3-EC0B-1FA6-5EF80E6E37DF">
<createdBy>Lenovo</createdBy>
<createdTime>2018-04-09 20:49:53 UTC</createdTime>
<ownerDesignName>script_JDeveloper</ownerDesignName>
</ForeignKey>
</foreignKeys>
<primaryKeys>
<PrimaryKey class="oracle.dbtools.crest.model.design.storage.sqlserver.v2k5.PKProxySqlServerv2k5" name="PK_L_MAT_PROVEEDOR" id="5DEF633A-B3F0-3E84-5349-83DDBE67BC81">
<createdBy>Lenovo</createdBy>
<createdTime>2018-04-09 20:49:53 UTC</createdTime>
<ownerDesignName>Diagrama de clases</ownerDesignName>
<clustered>true</clustered>
</PrimaryKey>
</primaryKeys>
</TableProxySqlServerv2k5>